odoo/addons/event_sale_free_no_invoiceable/README.rst
odoo/addons/event_sale_free_no_invoiceable/__init__.py
odoo/addons/event_sale_free_no_invoiceable/__manifest__.py
odoo/addons/event_sale_free_no_invoiceable/hooks.py
odoo/addons/event_sale_free_no_invoiceable/i18n/event_sale_free_no_invoiceable.pot
odoo/addons/event_sale_free_no_invoiceable/i18n/it.po
odoo/addons/event_sale_free_no_invoiceable/models/__init__.py
odoo/addons/event_sale_free_no_invoiceable/models/sale_order.py
odoo/addons/event_sale_free_no_invoiceable/readme/CONTRIBUTORS.md
odoo/addons/event_sale_free_no_invoiceable/readme/DESCRIPTION.md
odoo/addons/event_sale_free_no_invoiceable/readme/INSTALL.md
odoo/addons/event_sale_free_no_invoiceable/static/description/icon.png
odoo/addons/event_sale_free_no_invoiceable/static/description/index.html
odoo/addons/event_sale_free_no_invoiceable/tests/__init__.py
odoo/addons/event_sale_free_no_invoiceable/tests/test_event_sale_free_no_invoiceable.py
odoo_addon_event_sale_free_no_invoiceable-18.0.1.0.0.2.dist-info/METADATA
odoo_addon_event_sale_free_no_invoiceable-18.0.1.0.0.2.dist-info/WHEEL
odoo_addon_event_sale_free_no_invoiceable-18.0.1.0.0.2.dist-info/top_level.txt
odoo_addon_event_sale_free_no_invoiceable-18.0.1.0.0.2.dist-info/RECORD
